astrogator/__init__.py
astrogator/astrogator.py
astrogator-1.0.0.dist-info/LICENSE
astrogator-1.0.0.dist-info/METADATA
astrogator-1.0.0.dist-info/WHEEL
astrogator-1.0.0.dist-info/top_level.txt
astrogator-1.0.0.dist-info/RECORD
