Metadata-Version: 2.1
Name: astrogator
Version: 1.0.0
Summary: Astrogator: Your daily guide to the stars, offering personalized horoscopes with ease.
Home-page: https://github.com/your_username/horoscope_package
Author: Koustubh PK
Author-email: koustubhpk@example.com
License: MIT
Classifier: Programming Language :: Python :: 3
Classifier: License :: OSI Approved :: MIT License
Classifier: Operating System :: OS Independent
Requires-Python: >=3.6
License-File: LICENSE
Requires-Dist: requests
Requires-Dist: beautifulsoup4
